LICENSE
MANIFEST.in
README.rst
setup.cfg
setup.py
doc/Makefile
genpy/__init__.py
genpy/version.py
genpy.egg-info/PKG-INFO
genpy.egg-info/SOURCES.txt
genpy.egg-info/dependency_links.txt
genpy.egg-info/requires.txt
genpy.egg-info/top_level.txt
test/test_genpy.py