Metadata-Version: 1.2
Name: genpy
Version: 2022.1
Summary: AST-based generation of Python source code
Home-page: http://documen.tician.de/genpy/
Author: Andreas Kloeckner
Author-email: inform@tiker.net
License: MIT
Platform: UNKNOWN
Classifier: Development Status :: 4 - Beta
Classifier: Intended Audience :: Developers
Classifier: Intended Audience :: Other Audience
Classifier: Intended Audience :: Science/Research
Classifier: License :: OSI Approved :: MIT License
Classifier: Natural Language :: English
Classifier: Programming Language :: Python :: 3
Classifier: Topic :: Scientific/Engineering
Classifier: Topic :: Software Development :: Libraries
Classifier: Topic :: Utilities
Requires-Python: ~=3.6
